enstools/api.py
enstools/clustering/__init__.py
enstools/clustering/preparation.py
enstools/clustering/wrapper.py
enstools/core/__init__.py
enstools/core/batchjob.py
enstools/core/cluster.py
enstools/core/errors.py
enstools/core/os_support.py
enstools/core/parallelisation.py
enstools/core/tempdir.py
enstools/filters/DCT2D.py
enstools/filters/__init__.py
enstools/interpolation/__init__.py
enstools/interpolation/coarse_graining.py
enstools/interpolation/nearest_neighbour_interpolator.py
enstools/interpolation/vertical_interpolation.py
enstools/io/__init__.py
enstools/io/dataset.py
enstools/io/file_type.py
enstools/io/paths.py
enstools/io/reader.py
enstools/io/writer.py
enstools/io/eccodes/__init__.py
enstools/io/eccodes/eccodes_cffi.py
enstools/misc/__init__.py
enstools/opendata/DWDContent.py
enstools/opendata/DWDRadar.py
enstools/opendata/__init__.py
enstools/opendata/cli.py
enstools/opendata/retrieve_nwp.py
enstools/opendata/retrieve_radar.py
enstools/plot/__init__.py
enstools/plot/core.py
enstools/plot/ensemble.py
enstools/plot/interactive/__init__.py
enstools/plot/interactive/backend.py
enstools/plot/interactive/backend3D.py
enstools/plot/interactive/backend_bokeh.py
enstools/plot/interactive/backend_plotly.py
enstools/post/ConvectiveAdjustmentTimescale.py
enstools/post/EnsembleStat.py
enstools/post/Vorticity.py
enstools/post/__init__.py
enstools/scores/__init__.py
enstools/scores/continuous_ranked_probability_score.py
enstools/scores/fix_attributes.py
enstools/scores/kolmogorov_smirnov.py
enstools/scores/kolmogorov_smirnov_multicell.py
enstools/scores/normalized_root_mean_square_error.py
enstools/scores/peak_signal_to_noise_ratio.py
enstools/scores/pearson_correlation.py
enstools/scores/positivity.py
enstools/scores/structural_similarity_index.py
enstools/scores/template.py
enstools/scores/DisplacementAmplitudeScore/__init__.py
enstools/scores/DisplacementAmplitudeScore/calc_das.py
enstools/scores/DisplacementAmplitudeScore/match_pyramid_ic.py
enstools-2025.5.0.dist-info/LICENSE
enstools-2025.5.0.dist-info/METADATA
enstools-2025.5.0.dist-info/WHEEL
enstools-2025.5.0.dist-info/entry_points.txt
enstools-2025.5.0.dist-info/top_level.txt
enstools-2025.5.0.dist-info/RECORD
