Metadata-Version: 2.1
Name: enstools
Version: 2025.5.0
Home-page: https://github.com/wavestoweather/enstools
Author: Robert Redl et al.
Author-email: robert.redl@lmu.de
License-File: LICENSE
Requires-Dist: appdirs
Requires-Dist: numpy
Requires-Dist: xarray
Requires-Dist: cftime
Requires-Dist: dask
Requires-Dist: distributed
Requires-Dist: cloudpickle
Requires-Dist: colorama
Requires-Dist: numba
Requires-Dist: toolz
Requires-Dist: pint
Requires-Dist: matplotlib
Requires-Dist: decorator
Requires-Dist: multipledispatch
Requires-Dist: cachey
Requires-Dist: cffi
Requires-Dist: pandas
Requires-Dist: packaging
Requires-Dist: h5netcdf
Requires-Dist: h5py
Requires-Dist: numcodecs
Requires-Dist: requests
Requires-Dist: scikit-image
Requires-Dist: scikit-learn
Requires-Dist: scipy
Requires-Dist: statsmodels
Requires-Dist: dataclasses
Provides-Extra: compression
Requires-Dist: enstools-compression; extra == "compression"
Provides-Extra: plot
Requires-Dist: cartopy; extra == "plot"
Requires-Dist: plotly; extra == "plot"
Requires-Dist: bokeh; extra == "plot"
